asciinwriter/__init__.py
asciinwriter/__main__.py
asciinwriter-0.2.2.dist-info/LICENSES/GPL-3.0-or-later.txt
asciinwriter-0.2.2.dist-info/METADATA
asciinwriter-0.2.2.dist-info/WHEEL
asciinwriter-0.2.2.dist-info/entry_points.txt
asciinwriter-0.2.2.dist-info/RECORD
