Metadata-Version: 2.3
Name: asciinwriter
Version: 0.2.2
Summary: Script and automate interactive terminal sessions for generating asciinema .cast files and reproducible demos.
License: GPL-3.0-or-later
Keywords: asciinema,cast,terminal,automation,demo,gif,documentation
Author: Alexei Znamensky
Author-email: russoz@gmail.com
Requires-Python: >=3.11,<4.0
Classifier: Development Status :: 4 - Beta
Classifier: Environment :: Console
Classifier: Intended Audience :: Developers
Classifier: Intended Audience :: Information Technology
Classifier: Intended Audience :: System Administrators
Classifier: License :: OSI Approved :: GNU General Public License v3 or later (GPLv3+)
Classifier: Operating System :: OS Independent
Classifier: Programming Language :: Python
Classifier: Programming Language :: Python :: 3
Classifier: Programming Language :: Python :: 3.11
Classifier: Programming Language :: Python :: 3.12
Classifier: Programming Language :: Python :: 3.13
Classifier: Topic :: Software Development :: Documentation
Classifier: Topic :: Terminals
Classifier: Topic :: Utilities
Requires-Dist: argcomplete (>=3.5.3,<4.0.0)
Requires-Dist: pexpect (>=4.9.0,<5.0.0)
Project-URL: Bug Tracker, https://github.com/russoz/asciinwriter/issues
Project-URL: Homepage, https://github.com/russoz/asciinwriter
Project-URL: Repository, https://github.com/russoz/asciinwriter
